comfy_aimdo/_version.py
comfy_aimdo/control.py
comfy_aimdo/model_vbar.py
comfy_aimdo/torch.py
comfy_aimdo-0.1.6.dist-info/licenses/LICENSE
comfy_aimdo-0.1.6.dist-info/METADATA
comfy_aimdo-0.1.6.dist-info/WHEEL
comfy_aimdo-0.1.6.dist-info/top_level.txt
comfy_aimdo-0.1.6.dist-info/RECORD
