Metadata-Version: 2.4
Name: comfy-aimdo
Version: 0.1.6
Summary: AI Model Dynamic Offloader for ComfyUI
Author: rattus
Project-URL: Repository, https://github.com/Comfy-Org/comfy-aimdo
Requires-Python: >=3.9
License-File: LICENSE
Dynamic: license-file
